Workbook

Sheet Working
A1: Zidane Corporation - Rate working: Rajby Industries - PR# 217
A2: Markup on Buy High: | D2: 0.15 | E2: <- yellow cell change karo, selling rates update ho jayenge
A4: SR# | B4: Item Code | C4: Item Description | D4: UOM | E4: Qty | F4: Brand (quote) | G4: Buy Low | H4: Buy High | I4: Sell Rate | J4: Buy Total | K4: Sell Total | L4: Profit | M4: Margin | N4: Status V/S/N | O4: Src | P4: Source / Note
A5: 1 | B5: 825-00000245-00000-01-000-000 | C5: PROTRACTOR 80MMX120MM | D5: Number | E5: 3 | F5: Insize / Equivalent | G5: 7112 | H5: 7112 | I5: =ROUND(H5*(1+$D$2),-1) -> 8180 | J5: =E5*H5 -> 21336 | K5: =E5*I5 -> 24540 | L5: =K5-J5 -> 3204 | M5: =IF(K5=0,0,L5/K5) -> 0.13056235 | N5: S | O5: Intl | P5: industrybuying.com Insize 4799-180 protractor 80x120mm INR 2,123 (variant price confirm)
A6: 2 | B6: 515-01124945-00000-01-000-000 | C6: STAINLESS SCALE REMOVER 1KG | D6: Kilogram | E6: 24 | F6: K2 Pickling Paste / Equivalent | G6: 1297 | H6: 1843 | I6: =ROUND(H6*(1+$D$2),-1) -> 2120 | J6: =E6*H6 -> 44232 | K6: =E6*I6 -> 50880 | L6: =K6-J6 -> 6648 | M6: =IF(K6=0,0,L6/K6) -> 0.13066038 | N6: S | O6: Intl | P6: indiamart K2 pickling paste INR 387-550/kg; branded UK Super 6 GBP 41.20/2kg = 8,620/kg option
A7: 3 | B7: 515-01124947-00000-01-000-000 | C7: LASER LEVEL WITH TRIPOAD, SELF LEVELING 3LINES 360 DEGREE RANGE 30M | D7: Number | E7: 1 | F7: Bosch Professional | G7: 171970 | H7: 174720 | I7: =ROUND(H7*(1+$D$2),-1) -> 200930 | J7: =E7*H7 -> 174720 | K7: =E7*I7 -> 200930 | L7: =K7-J7 -> 26210 | M7: =IF(K7=0,0,L7/K7) -> 0.13044344 | N7: V | O7: PK | P7: toolsmart.pk Bosch GLL 3-80 P 155,220 + BT150 tripod toolsmart 16,750 / ktools 19,500
A8: 4 | B8: 515-01124954-00000-01-000-000 | C8: HYDRO CHROLIC ACID | D8: Kilogram | E8: 20 | F8: Local | G8: 120 | H8: 200 | I8: =ROUND(H8*(1+$D$2),-1) -> 230 | J8: =E8*H8 -> 4000 | K8: =E8*I8 -> 4600 | L8: =K8-J8 -> 600 | M8: =IF(K8=0,0,L8/K8) -> 0.13043478 | N8: N | O8: PK | P8: No online listing - local chemical market estimate (33% commercial, 25kg can)
A9: 5 | B9: 515-01125003-00000-01-000-000 | C9: DIAL INDICATOR MAGNETIC STAND | D9: Number | E9: 1 | F9: Insize | G9: 4200 | H9: 5700 | I9: =ROUND(H9*(1+$D$2),-1) -> 6560 | J9: =E9*H9 -> 5700 | K9: =E9*I9 -> 6560 | L9: =K9-J9 -> 860 | M9: =IF(K9=0,0,L9/K9) -> 0.13109756 | N9: V | O9: PK | P9: ktools.pk Insize 6200-60 magnetic stand 5,700; kamadi.pk 4,200
A10: 6 | B10: 515-01125004-00000-01-000-000 | C10: PRECISION DIAL INDICATOR | D10: Number | E10: 1 | F10: Insize / Equivalent | G10: 10350 | H10: 10350 | I10: =ROUND(H10*(1+$D$2),-1) -> 11900 | J10: =E10*H10 -> 10350 | K10: =E10*I10 -> 11900 | L10: =K10-J10 -> 1550 | M10: =IF(K10=0,0,L10/K10) -> 0.1302521 | N10: V | O10: Intl | P10: anaum.com (UAE) Insize 2308-10A 10mm x 0.01mm AED 115
A11: 7 | B11: 515-01125005-00000-01-000-000 | C11: STUD BOLT SCREW DRILL EXTRACTOR KIT BROKEN REMOVAL SET (IMPERIAL METRIC) | D11: Number | E11: 3 | F11: Yato / Equivalent | G11: 9573 | H11: 11421 | I11: =ROUND(H11*(1+$D$2),-1) -> 13130 | J11: =E11*H11 -> 34263 | K11: =E11*I11 -> 39390 | L11: =K11-J11 -> 5127 | M11: =IF(K11=0,0,L11/K11) -> 0.13015994 | N11: V | O11: Intl | P11: toya24.pl Yato YT-06034 25pc extractor set PLN 126.20; kaufland.pl PLN 105.78
A12: 8 | B12: 515-01125026-00000-01-000-000 | C12: DUROMETER SHORE A | D12: Number | E12: 3 | F12: Insize / Equivalent | G12: 41472 | H12: 51011 | I12: =ROUND(H12*(1+$D$2),-1) -> 58660 | J12: =E12*H12 -> 153033 | K12: =E12*I12 -> 175980 | L12: =K12-J12 -> 22947 | M12: =IF(K12=0,0,L12/K12) -> 0.1303955 | N12: V | O12: Intl | P12: shop.k-met.com Insize ISH-SAM Shore A EUR 132.84 incl tax (108 ex)
A13: 9 | B13: 515-01125027-00000-01-000-000 | C13: THREAD GAUGE | D13: Number | E13: 1 | F13: Insize / Equivalent | G13: 5096 | H13: 5577 | I13: =ROUND(H13*(1+$D$2),-1) -> 6410 | J13: =E13*H13 -> 5577 | K13: =E13*I13 -> 6410 | L13: =K13-J13 -> 833 | M13: =IF(K13=0,0,L13/K13) -> 0.1299532 | N13: V | O13: Intl | P13: techno.my Insize 4820-452 pitch gauge metric+whitworth MYR 71.50; organametrisis.gr EUR 10.70 ex VAT
A14: 10 | B14: 515-01125047-00000-01-000-000 | C14: KNURLING TOOL 07PCS (0.5MM,1MM,1.5MM) | D14: Number | E14: 2 | F14: Taiwan / Equivalent | G14: 29375 | H14: 29375 | I14: =ROUND(H14*(1+$D$2),-1) -> 33780 | J14: =E14*H14 -> 58750 | K14: =E14*I14 -> 67560 | L14: =K14-J14 -> 8810 | M14: =IF(K14=0,0,L14/K14) -> 0.13040261 | N14: S | O14: Intl | P14: vxb.com knurling set 0.5/1.0/1.5mm L+R wheels with holder USD 88.88 (7pc helical with point box - confirm)
A15: 11 | B15: 515-01125051-00000-01-000-000 | C15: LIFTING BELT CAPACITY 5 TON LENGTH 3MTR | D15: Number | E15: 4 | F15: Taiwan / Equivalent | G15: 6909 | H15: 8640 | I15: =ROUND(H15*(1+$D$2),-1) -> 9940 | J15: =E15*H15 -> 34560 | K15: =E15*I15 -> 39760 | L15: =K15-J15 -> 5200 | M15: =IF(K15=0,0,L15/K15) -> 0.13078471 | N15: S | O15: Intl | P15: safetyliftingear.com 5T webbing sling 2m GBP 16.51 (3m listed nahi, +25% est)
A16: 12 | B16: 515-01125052-00000-01-000-000 | C16: LIFTING BELT CAPACITY 5 TON LENGTH 4MTR | D16: Number | E16: 4 | F16: Taiwan / Equivalent | G16: 8640 | H16: 10370 | I16: =ROUND(H16*(1+$D$2),-1) -> 11930 | J16: =E16*H16 -> 41480 | K16: =E16*I16 -> 47720 | L16: =K16-J16 -> 6240 | M16: =IF(K16=0,0,L16/K16) -> 0.13076278 | N16: S | O16: Intl | P16: safetyliftingear.com 5T webbing sling 2m GBP 16.51 (4m listed nahi, +50% est)
... A29: 25 | B29: 825-00000278-00000-01-000-000 | C29: LASER MEASUREMENT TAPE RANGE 250M | D29: Number | E29: 1 | F29: Bosch Professional | G29: 114200 | H29: 131000 | I29: =ROUND(H29*(1+$D$2),-1) -> 150650 | J29: =E29*H29 -> 131000 | K29: =E29*I29 -> 150650 | L29: =K29-J29 -> 19650 | M29: =IF(K29=0,0,L29/K29) -> 0.13043478 | N29: V | O29: PK | P29: kamadi.pk Bosch GLM 250 VF 114,200; ktools.pk 131,000
C30: TOTAL | J30: =SUM(J5:J29) -> 1271306 | K30: =SUM(K5:K29) -> 1462100 | L30: =SUM(L5:L29) -> 190794 | M30: =IF(K30=0,0,L30/K30) -> 0.13049313
A32: Status: V = exact listing, S = size/pack/brand differs (estimate in note), N = no online listing. Src: PK = Pakistani seller; Intl = UAE/UK/US/EU/IN/MY rate converted (AED x90, USD x330.5, GBP x418.5, EUR x384, PLN x90.5, MYR x78, INR x3.35).

Sheet Quotation
A1: Zidane Corporation - QUOTATION
A2: Reference: Rajby Industries - PR# 217 Currency: PKR Date: 12-Oct-2026
A4: SR# | B4: Item Code | C4: Item Description | D4: Brand | E4: UOM | F4: Qty | G4: Unit Rate (PKR) | H4: Amount (PKR)
A5: 1 | B5: 825-00000245-00000-01-000-000 | C5: PROTRACTOR 80MMX120MM | D5: Insize / Equivalent | E5: Number | F5: 3 | G5: =Working!I5 -> 8180 | H5: =F5*G5 -> 24540
A6: 2 | B6: 515-01124945-00000-01-000-000 | C6: STAINLESS SCALE REMOVER 1KG | D6: K2 Pickling Paste / Equivalent | E6: Kilogram | F6: 24 | G6: =Working!I6 -> 2120 | H6: =F6*G6 -> 50880
A7: 3 | B7: 515-01124947-00000-01-000-000 | C7: LASER LEVEL WITH TRIPOAD, SELF LEVELING 3LINES 360 DEGREE RANGE 30M | D7: Bosch Professional | E7: Number | F7: 1 | G7: =Working!I7 -> 200930 | H7: =F7*G7 -> 200930
A8: 4 | B8: 515-01124954-00000-01-000-000 | C8: HYDRO CHROLIC ACID | D8: Local | E8: Kilogram | F8: 20 | G8: =Working!I8 -> 230 | H8: =F8*G8 -> 4600
A9: 5 | B9: 515-01125003-00000-01-000-000 | C9: DIAL INDICATOR MAGNETIC STAND | D9: Insize | E9: Number | F9: 1 | G9: =Working!I9 -> 6560 | H9: =F9*G9 -> 6560
A10: 6 | B10: 515-01125004-00000-01-000-000 | C10: PRECISION DIAL INDICATOR | D10: Insize / Equivalent | E10: Number | F10: 1 | G10: =Working!I10 -> 11900 | H10: =F10*G10 -> 11900
A11: 7 | B11: 515-01125005-00000-01-000-000 | C11: STUD BOLT SCREW DRILL EXTRACTOR KIT BROKEN REMOVAL SET (IMPERIAL METRIC) | D11: Yato / Equivalent | E11: Number | F11: 3 | G11: =Working!I11 -> 13130 | H11: =F11*G11 -> 39390
A12: 8 | B12: 515-01125026-00000-01-000-000 | C12: DUROMETER SHORE A | D12: Insize / Equivalent | E12: Number | F12: 3 | G12: =Working!I12 -> 58660 | H12: =F12*G12 -> 175980
A13: 9 | B13: 515-01125027-00000-01-000-000 | C13: THREAD GAUGE | D13: Insize / Equivalent | E13: Number | F13: 1 | G13: =Working!I13 -> 6410 | H13: =F13*G13 -> 6410
A14: 10 | B14: 515-01125047-00000-01-000-000 | C14: KNURLING TOOL 07PCS (0.5MM,1MM,1.5MM) | D14: Taiwan / Equivalent | E14: Number | F14: 2 | G14: =Working!I14 -> 33780 | H14: =F14*G14 -> 67560
A15: 11 | B15: 515-01125051-00000-01-000-000 | C15: LIFTING BELT CAPACITY 5 TON LENGTH 3MTR | D15: Taiwan / Equivalent | E15: Number | F15: 4 | G15: =Working!I15 -> 9940 | H15: =F15*G15 -> 39760
A16: 12 | B16: 515-01125052-00000-01-000-000 | C16: LIFTING BELT CAPACITY 5 TON LENGTH 4MTR | D16: Taiwan / Equivalent | E16: Number | F16: 4 | G16: =Working!I16 -> 11930 | H16: =F16*G16 -> 47720
... A29: 25 | B29: 825-00000278-00000-01-000-000 | C29: LASER MEASUREMENT TAPE RANGE 250M | D29: Bosch Professional | E29: Number | F29: 1 | G29: =Working!I29 -> 150650 | H29: =F29*G29 -> 150650
G30: TOTAL | H30: =SUM(H5:H29) -> 1462100
